{
  "repos": [
    {
      "url": "https://github.com/borisyankov/DefinitelyTyped.git",
      "ref": "master"
    },
    {
      "url": "https://gist.github.com/c3d5420057bcb554dc11.git",
      "ref": "master"
    }
  ],
  "path": "typings",
  "bundle": "typings/tsd.d.ts",
  "link": {
    "npm": {
      "include": true
    }
  },
  "dependencies": {
    "text-encoding/text-encoding.d.ts": {
      "ref": "43f4fc592a99e2f0f8f4ee3ae26a3a8e2f5ca3ae"
    },
    "encoding-japanese/encoding.d.ts": {
      "repo": "https://gist.github.com/c3d5420057bcb554dc11.git",
      "ref": "6300974eab5d6f02719f505d45d4bcf9fee36c5c",
      "path": "encoding.d.ts"
    },
    "surfaces_yaml/surfaces_yaml.d.ts": {
      "repo": "https://gist.github.com/c3d5420057bcb554dc11.git",
      "ref": "6300974eab5d6f02719f505d45d4bcf9fee36c5c",
      "path": "surfaces_yaml.d.ts"
    },
    "jszip/jszip.d.ts": {
      "ref": "43f4fc592a99e2f0f8f4ee3ae26a3a8e2f5ca3ae"
    },
    "eventemitter2/eventemitter2.d.ts": {
      "ref": "43f4fc592a99e2f0f8f4ee3ae26a3a8e2f5ca3ae"
    },
    "jquery/jquery.d.ts": {
      "ref": "43f4fc592a99e2f0f8f4ee3ae26a3a8e2f5ca3ae"
    },
    "NarLoader/NarLoader.d.ts": {
      "repo": "https://gist.github.com/c3d5420057bcb554dc11.git",
      "ref": "6300974eab5d6f02719f505d45d4bcf9fee36c5c",
      "path": "NarLoader.d.ts"
    },
    "qunit/qunit.d.ts": {
      "ref": "43f4fc592a99e2f0f8f4ee3ae26a3a8e2f5ca3ae"
    }
  }
}